{
  "ComponentIndexes": {},
  "ControlUniqueGuids": {},
  "ControlUniqueIds": {
    "Apellidos_DataCard1": 192,
    "Apellidos_DataCard2": 297,
    "Apellidos_DataCard3": 15,
    "App": 1,
    "Body1": 243,
    "Boton_Entrar_Login": 261,
    "Boton_PUAV_Aceptar_Invierno": 138,
    "Boton_PUAV_Aceptar_Verano": 154,
    "Boton_PUAV_Cancelar": 89,
    "Boton_PUAV_Cancelar_Invierno": 136,
    "Boton_PUAV_Cancelar_Verano": 153,
    "Boton_PUAV_Comprobar_Verano": 155,
    "Boton_PUAV_Invierno": 134,
    "Boton_PUAV_Verano": 132,
    "Boton_PUMV_Aceptar_Invierno": 144,
    "Boton_PUMV_Aceptar_Verano": 157,
    "Boton_PUMV_Cancelar": 94,
    "Boton_PUMV_Cancelar_Invierno": 143,
    "Boton_PUMV_Cancelar_Verano": 156,
    "Boton_PUMV_Comprobar_Verano": 158,
    "Boton_PUMV_Invierno": 140,
    "Boton_PUMV_Verano": 139,
    "BotonAñadirBaja": 68,
    "BotonAñadirDAP": 71,
    "BotonAñadirDLE": 69,
    "BotonAñadirVacaciones": 65,
    "BotonCalcularCalendario": 64,
    "BotonConfigurarCalendario": 73,
    "botonEnviar": 339,
    "BotonModificarDLE": 70,
    "BotonModificarVacaciones": 67,
    "botonNuevo": 337,
    "BotonPortalEmpleados": 74,
    "botonReinicio": 338,
    "btn_aceptar_baja": 152,
    "btn_aceptar_PUAAP": 146,
    "btn_aceptar_PUALE": 150,
    "btn_aceptar_PUMLE": 148,
    "btn_cancelar_baja": 151,
    "btn_cancelar_PUAAP": 145,
    "btn_cancelar_PUALE": 149,
    "btn_cancelar_PUMLE": 147,
    "Button1": 50,
    "Button2": 250,
    "Button2_2": 286,
    "Button7_5": 72,
    "ButtonAceptar": 60,
    "Buttoncancelar": 220,
    "Buttonconfirmar": 221,
    "ButtonEnviar": 61,
    "Calendario": 63,
    "ConfiguracionCalendario": 262,
    "Consulta": 172,
    "ConsultaEmpleadosTitle": 177,
    "ConsultarVacaciones": 340,
    "Contraseña_DataCard1": 307,
    "Contraseña_DataCard2": 25,
    "Cuadro_Espera": 75,
    "Cuadro_PUAV": 86,
    "Cuadro_PUAV_Invierno": 88,
    "Cuadro_PUAV_Invierno_1": 109,
    "Cuadro_PUAV_Verano": 77,
    "Cuadro_PUAV_Verano_1": 78,
    "Cuadro_PUMV": 93,
    "DataCardKey1": 294,
    "DataCardKey10": 314,
    "DataCardKey11": 329,
    "DataCardKey12": 334,
    "DataCardKey13": 309,
    "DataCardKey14": 17,
    "DataCardKey15": 12,
    "DataCardKey16": 22,
    "DataCardKey17": 32,
    "DataCardKey18": 47,
    "DataCardKey19": 54,
    "DataCardKey2": 190,
    "DataCardKey20": 324,
    "DataCardKey21": 319,
    "DataCardKey22": 27,
    "DataCardKey23": 37,
    "DataCardKey24": 42,
    "DataCardKey25": 204,
    "DataCardKey26": 207,
    "DataCardKey3": 193,
    "DataCardKey4": 197,
    "DataCardKey5": 201,
    "DataCardKey6": 210,
    "DataCardKey7": 214,
    "DataCardKey8": 299,
    "DataCardKey9": 304,
    "DataCardValue1": 191,
    "DataCardValue10": 315,
    "DataCardValue11": 335,
    "DataCardValue12": 310,
    "DataCardValue13": 18,
    "DataCardValue14": 13,
    "DataCardValue15": 23,
    "DataCardValue16": 33,
    "DataCardValue17": 55,
    "DataCardValue18": 325,
    "DataCardValue19": 320,
    "DataCardValue2": 194,
    "DataCardValue20": 28,
    "DataCardValue21": 38,
    "DataCardValue22": 43,
    "DataCardValue23": 205,
    "DataCardValue24": 208,
    "DataCardValue3": 198,
    "DataCardValue4": 202,
    "DataCardValue5": 211,
    "DataCardValue6": 215,
    "DataCardValue7": 295,
    "DataCardValue8": 300,
    "DataCardValue9": 305,
    "Datos adjuntos_DataCard1": 212,
    "Datos adjuntos_DataCard2": 332,
    "Datos adjuntos_DataCard3": 52,
    "Departamento_DataCard1": 195,
    "Departamento_DataCard2": 312,
    "Departamento_DataCard3": 30,
    "Departamentos": 235,
    "DiasSemana": 170,
    "DNI_DataCard1": 317,
    "DNI_DataCard2": 35,
    "DNI_DataCard3": 203,
    "dp_ALE1": 129,
    "dp_ALE2": 121,
    "dp_Fecha_PUAAP": 127,
    "dp_Fin_Verano": 284,
    "dp_FinInvierno": 278,
    "dp_FinInvierno2": 285,
    "dp_FinPeticion": 283,
    "dp_inicio_baja": 126,
    "dp_InicioInvierno": 275,
    "dp_InicioInvierno2": 282,
    "dp_InicioPeticion": 276,
    "dp_InicioVerano": 277,
    "dp_MLE1": 124,
    "dp_MLE2": 133,
    "dp_PUAV_Dia_Inicio_Verano_1": 119,
    "dp_PUAV_Dia_Inicio_Verano_2": 131,
    "dp_PUAV_Dia_Inicio_Verano_3": 137,
    "dp_PUMV_Dia_Inicio_Verano_1": 123,
    "dp_PUMV_Dia_Inicio_Verano_2": 135,
    "dp_PUMV_Dia_Inicio_Verano_3": 142,
    "Dropdown1": 245,
    "Dropdown2": 362,
    "Dropdown4": 371,
    "ErrorMessage1": 296,
    "ErrorMessage10": 14,
    "ErrorMessage11": 24,
    "ErrorMessage12": 34,
    "ErrorMessage13": 51,
    "ErrorMessage14": 56,
    "ErrorMessage15": 311,
    "ErrorMessage16": 326,
    "ErrorMessage17": 321,
    "ErrorMessage18": 29,
    "ErrorMessage19": 39,
    "ErrorMessage2": 199,
    "ErrorMessage20": 44,
    "ErrorMessage3": 216,
    "ErrorMessage4": 301,
    "ErrorMessage5": 306,
    "ErrorMessage6": 316,
    "ErrorMessage7": 331,
    "ErrorMessage8": 336,
    "ErrorMessage9": 19,
    "EsAdmin_DataCard1": 322,
    "EsAdmin_DataCard2": 40,
    "EsAdmin_DataCard3": 206,
    "Fecha Nacimiento_DataCard1": 200,
    "Fecha Nacimiento_DataCard2": 302,
    "Fecha Nacimiento_DataCard3": 20,
    "FiltroDepartamento": 178,
    "Firma_DataCard1": 327,
    "Firma_DataCard2": 209,
    "Firma_DataCard3": 45,
    "FlechaSiguiente": 184,
    "FondoPopUp": 66,
    "FormNuevoEmpleado": 291,
    "FormularioEmpleados": 188,
    "FormularioModificar": 9,
    "GaleriaNombres": 180,
    "GaleriaNombrestemplate1": 181,
    "Gallery1": 239,
    "Gallery2": 344,
    "GalleryCalendario": 114,
    "galleryTemplate1": 240,
    "galleryTemplate2": 345,
    "galleryTemplate3": 115,
    "Host": 3,
    "Icon1": 227,
    "Icon1_1": 238,
    "Icon2": 265,
    "Icon221": 232,
    "Icon223": 233,
    "Icon3": 234,
    "Icon4": 343,
    "IconInfo": 58,
    "Icono_No_Ver_Contraseña": 259,
    "Icono_Ver_Contraseña": 260,
    "IconoAlerta": 218,
    "IconoBorrar": 223,
    "IconoBusqueda": 175,
    "IconoDerecha": 108,
    "IconoIzquierda": 99,
    "IconoModificar": 222,
    "IconoRetroceso": 289,
    "IconoVolver": 176,
    "IconRetrocede": 8,
    "Image1": 253,
    "Image4": 49,
    "ImagenInvescon": 183,
    "Label_espera": 102,
    "Label1": 96,
    "Label10": 92,
    "Label11": 264,
    "Label12": 273,
    "Label12_1": 274,
    "Label12_2": 272,
    "Label12_3": 280,
    "Label12_4": 281,
    "Label12_5": 279,
    "Label12_6": 270,
    "Label12_7": 271,
    "Label12_8": 269,
    "Label13": 244,
    "Label13_1": 248,
    "Label13_2": 246,
    "Label14": 249,
    "Label15": 342,
    "Label16": 357,
    "Label17": 358,
    "Label18": 359,
    "Label2": 97,
    "Label2_1": 110,
    "Label20": 361,
    "Label21": 363,
    "Label22": 364,
    "Label22_1": 366,
    "Label221": 228,
    "Label221_1": 237,
    "Label3": 90,
    "Label4": 255,
    "Label5": 257,
    "Label6": 254,
    "Label7": 95,
    "Label7_1": 111,
    "Label8": 118,
    "Label8_1": 122,
    "Label9": 98,
    "Label9_2": 84,
    "Label9_3": 112,
    "Label9_4": 128,
    "Label9_5": 83,
    "Label9_6": 113,
    "Label9_7": 130,
    "LabelAño": 87,
    "LabelDiaCal": 117,
    "LabelDomingo": 107,
    "LabelEventoCal": 116,
    "LabelJueves": 104,
    "LabelLunes": 100,
    "LabelMartes": 101,
    "LabelMes": 80,
    "LabelMiercoles": 103,
    "LabelSabado": 106,
    "LabelViernes": 105,
    "Login": 251,
    "Modificar": 4,
    "Nombre_DataCard1": 189,
    "Nombre_DataCard2": 292,
    "Nombre_DataCard4": 10,
    "NombreApellido": 185,
    "Nuevo": 287,
    "PenInput1": 330,
    "PenInput2": 48,
    "PopUp_AñadirAP": 168,
    "PopUp_AñadirLE": 161,
    "PopUp_Baja": 165,
    "PopUp_ModificarLE": 164,
    "PopUpAñadirVacaciones": 166,
    "PopupCambio": 62,
    "PopUpEliminar": 224,
    "PopUpModificarVacaciones": 169,
    "PUAV_Invierno": 167,
    "PUAV_Verano": 162,
    "PUMV_Invierno": 171,
    "PUMV_Verano": 163,
    "rb_PUAV_Invierno": 120,
    "rb_PUAV_Verano": 82,
    "rb_PUMV_Invierno": 125,
    "rb_PUMV_Verano": 81,
    "Rectangle1": 85,
    "Rectangle10": 356,
    "Rectangle1Sup": 5,
    "Rectangle2": 76,
    "Rectangle221": 226,
    "Rectangle221_1": 236,
    "Rectangle223": 229,
    "Rectangle223_1": 231,
    "Rectangle224": 230,
    "Rectangle3": 91,
    "Rectangle4": 252,
    "Rectangle5": 79,
    "Rectangle6": 263,
    "Rectangle7": 266,
    "Rectangle7_1": 268,
    "Rectangle7_2": 267,
    "Rectangle8": 341,
    "RectangleGen": 174,
    "RectangleModificar": 6,
    "RectanglePopModificado": 57,
    "RectanglePopUpEliminar": 217,
    "RectangleSup": 288,
    "RectangleSuperior": 173,
    "RectanguloEmpleado": 182,
    "ScInicial": 225,
    "Separator2": 355,
    "SeparatorEmpleado": 187,
    "StarVisible1": 293,
    "StarVisible10": 11,
    "StarVisible11": 21,
    "StarVisible12": 31,
    "StarVisible13": 46,
    "StarVisible14": 53,
    "StarVisible15": 308,
    "StarVisible16": 323,
    "StarVisible17": 318,
    "StarVisible18": 26,
    "StarVisible19": 36,
    "StarVisible2": 196,
    "StarVisible20": 41,
    "StarVisible3": 213,
    "StarVisible4": 298,
    "StarVisible5": 303,
    "StarVisible6": 313,
    "StarVisible7": 328,
    "StarVisible8": 333,
    "StarVisible9": 16,
    "Subtitle2": 242,
    "SubtitleDepartamento": 186,
    "TextInput1": 247,
    "TextInput2": 365,
    "TextModificado": 59,
    "TextoBusqueda": 179,
    "TextoPopUpEliminar": 219,
    "Title2": 241,
    "TituloModificar": 7,
    "tituloNuevoEmpleado": 290,
    "TopBar": 159,
    "txt_Contraseña_Login": 258,
    "txt_duracion_baja": 141,
    "txt_Usuario_Login": 256,
    "VentanaEspera": 160
  },
  "FunctionParamsInvariantScripts": {},
  "FunctionParamsInvariantScriptsOnInstances": {},
  "HeaderLastSavedDateTimeUTC": "04/15/2024 12:24:41",
  "IsLegacyComponentAllowGlobalScopeCase": false,
  "LocalConnectionIDReferences": {
    "129484a6-239e-431b-a34f-d24fb22b69b7": "\"/providers/microsoft.powerapps/apis/shared_office365/connections/c9cc2931d5ba4d1a80ef2165833840d9\"",
    "315676ab-648e-47f7-a566-c934b2314bec": "\"/providers/microsoft.powerapps/apis/shared_excel/connections/090453d77df84ca289ebc83350dbf749\"",
    "b16987c8-2212-4b43-9140-4a40e64742e4": "\"/providers/microsoft.powerapps/apis/shared_sharepointonline/connections/9580306d292b4422a18c71da26238d64\"",
    "d195d75e-44f8-45ad-8bc0-eefcb7fb9574": "\"/providers/microsoft.powerapps/apis/shared_onedriveforbusiness/connections/4a9bf3a99ba04208990293fb94084bb9\""
  },
  "LocalDatabaseReferencesAsEmpty": true,
  "LocalResourceFileNames": {
    "logo": "0001.png",
    "vacaciones": "0002.png"
  },
  "LocalResourceRootPaths": {
    "logo": "https://docserverpwaprodweu.blob.core.windows.net/e09c4a14-ab23-42d5-9240-e13689f24d10-1/resource/Assets0Images00001.png?skoid=58690ece-ec83-4ce2-9ce8-883d4d6a54ee&sktid=975f013f-7f24-47e8-a7d3-abc4752bf346&skt=2024-04-15T07%3A03%3A06Z&ske=2024-04-16T07%3A18%3A06Z&sks=b&skv=2022-11-02&sv=2022-11-02&spr=https&se=2024-04-16T07%3A18%3A06Z&sr=b&sp=r&sig=OMaOFCb7WVlV75vfMWpimPp2Kn6K9a4eMeTBYIVIAv8%3D",
    "vacaciones": "https://docserverpwaprodweu.blob.core.windows.net/e09c4a14-ab23-42d5-9240-e13689f24d10-1/resource/Assets0Images00002.png?skoid=58690ece-ec83-4ce2-9ce8-883d4d6a54ee&sktid=975f013f-7f24-47e8-a7d3-abc4752bf346&skt=2024-04-15T07%3A03%3A06Z&ske=2024-04-16T07%3A18%3A06Z&sks=b&skv=2022-11-02&sv=2022-11-02&spr=https&se=2024-04-16T07%3A18%3A06Z&sr=b&sp=r&sig=gLQau1xNhAhXlrFiH%2Fot2c8u1ntZxmzkh4sAPZunIAM%3D"
  },
  "OldLogoFileName": "logo.jpg",
  "OrderComponentMetadata": {},
  "OrderComponentTemplate": {},
  "OrderDataSource": {
    "coll_mes": 12,
    "Coll_usuarios": 13,
    "Coll_vacaciones": 18,
    "collFestivos": 11,
    "ComboBoxSample": 1,
    "ConfiguracionCalendario_1": 2,
    "CustomGallerySample": 3,
    "Departamentos_1": 4,
    "DiasFestivos": 5,
    "DropDownSample": 6,
    "Empleados": 7,
    "Fiestas": 8,
    "hayfestivo": 14,
    "hayfestivo2": 15,
    "haypuente": 16,
    "lunesfiesta": 17,
    "Office365Outlook": 0,
    "RadioSample": 9,
    "Vacaciones": 10
  },
  "OrderGroupControls": {
    "DiasSemana": {
      "LabelDomingo": 6,
      "LabelJueves": 3,
      "LabelLunes": 0,
      "LabelMartes": 1,
      "LabelMiercoles": 2,
      "LabelSabado": 5,
      "LabelViernes": 4
    },
    "PopUp_AñadirAP": {
      "btn_aceptar_PUAAP": 4,
      "btn_cancelar_PUAAP": 3,
      "dp_Fecha_PUAAP": 2,
      "Label9": 1,
      "Rectangle3": 0
    },
    "PopUp_AñadirLE": {
      "btn_aceptar_PUALE": 5,
      "btn_cancelar_PUALE": 4,
      "dp_ALE1": 3,
      "dp_ALE2": 2,
      "Label3": 1,
      "Rectangle2": 0
    },
    "PopUp_Baja": {
      "btn_aceptar_baja": 5,
      "btn_cancelar_baja": 4,
      "dp_inicio_baja": 2,
      "Label1": 1,
      "Rectangle1": 0,
      "txt_duracion_baja": 3
    },
    "PopUp_ModificarLE": {
      "btn_aceptar_PUMLE": 5,
      "btn_cancelar_PUMLE": 4,
      "dp_MLE1": 2,
      "dp_MLE2": 3,
      "Label10": 1,
      "Rectangle5": 0
    },
    "PopUpAñadirVacaciones": {
      "Boton_PUAV_Cancelar": 4,
      "Boton_PUAV_Invierno": 3,
      "Boton_PUAV_Verano": 2,
      "Cuadro_PUAV": 0,
      "Label2": 1
    },
    "PopupCambio": {
      "ButtonAceptar": 3,
      "IconInfo": 2,
      "RectanglePopModificado": 0,
      "TextModificado": 1
    },
    "PopUpEliminar": {
      "Buttoncancelar": 4,
      "Buttonconfirmar": 3,
      "IconoAlerta": 1,
      "RectanglePopUpEliminar": 0,
      "TextoPopUpEliminar": 2
    },
    "PopUpModificarVacaciones": {
      "Boton_PUMV_Cancelar": 4,
      "Boton_PUMV_Invierno": 3,
      "Boton_PUMV_Verano": 2,
      "Cuadro_PUMV": 0,
      "Label2_1": 1
    },
    "PUAV_Invierno": {
      "Boton_PUAV_Aceptar_Invierno": 2,
      "Boton_PUAV_Cancelar_Invierno": 1,
      "Cuadro_PUAV_Invierno": 0,
      "Label7": 3,
      "rb_PUAV_Invierno": 4
    },
    "PUAV_Verano": {
      "Boton_PUAV_Aceptar_Verano": 1,
      "Boton_PUAV_Cancelar_Verano": 2,
      "Boton_PUAV_Comprobar_Verano": 11,
      "Cuadro_PUAV_Verano": 0,
      "dp_PUAV_Dia_Inicio_Verano_1": 9,
      "dp_PUAV_Dia_Inicio_Verano_2": 10,
      "dp_PUAV_Dia_Inicio_Verano_3": 4,
      "Label8": 3,
      "Label9_2": 5,
      "Label9_3": 7,
      "Label9_4": 8,
      "rb_PUAV_Verano": 6
    },
    "PUMV_Invierno": {
      "Boton_PUMV_Aceptar_Invierno": 2,
      "Boton_PUMV_Cancelar_Invierno": 1,
      "Cuadro_PUAV_Invierno_1": 0,
      "Label7_1": 3,
      "rb_PUMV_Invierno": 4
    },
    "PUMV_Verano": {
      "Boton_PUMV_Aceptar_Verano": 1,
      "Boton_PUMV_Cancelar_Verano": 2,
      "Boton_PUMV_Comprobar_Verano": 11,
      "Cuadro_PUAV_Verano_1": 0,
      "dp_PUMV_Dia_Inicio_Verano_1": 9,
      "dp_PUMV_Dia_Inicio_Verano_2": 10,
      "dp_PUMV_Dia_Inicio_Verano_3": 4,
      "Label8_1": 3,
      "Label9_5": 5,
      "Label9_6": 7,
      "Label9_7": 8,
      "rb_PUMV_Verano": 6
    },
    "TopBar": {
      "BotonAñadirBaja": 2,
      "BotonAñadirDAP": 5,
      "BotonAñadirDLE": 3,
      "BotonAñadirVacaciones": 0,
      "BotonConfigurarCalendario": 7,
      "BotonModificarDLE": 4,
      "BotonModificarVacaciones": 1,
      "BotonPortalEmpleados": 8,
      "Button7_5": 6
    },
    "VentanaEspera": {
      "Cuadro_Espera": 0,
      "Label_espera": 1
    }
  },
  "OrderPcfTemplate": {},
  "OrderTemplate": {},
  "OrderXMLTemplate": {
    "attachments": 11,
    "button": 10,
    "combobox": 6,
    "datepicker": 5,
    "dropdown": 14,
    "form": 3,
    "formViewer": 15,
    "gallery": 13,
    "icon": 2,
    "image": 9,
    "inkControl": 8,
    "label": 1,
    "radio": 12,
    "rectangle": 0,
    "text": 4,
    "toggleSwitch": 7
  },
  "OverridablePropertiesEntry": {
    "Apellidos_DataCard1": {},
    "Apellidos_DataCard2": {},
    "Apellidos_DataCard3": {},
    "App": {},
    "Body1": {},
    "Boton_Entrar_Login": {},
    "Boton_PUAV_Aceptar_Invierno": {},
    "Boton_PUAV_Aceptar_Verano": {},
    "Boton_PUAV_Cancelar": {},
    "Boton_PUAV_Cancelar_Invierno": {},
    "Boton_PUAV_Cancelar_Verano": {},
    "Boton_PUAV_Comprobar_Verano": {},
    "Boton_PUAV_Invierno": {},
    "Boton_PUAV_Verano": {},
    "Boton_PUMV_Aceptar_Invierno": {},
    "Boton_PUMV_Aceptar_Verano": {},
    "Boton_PUMV_Cancelar": {},
    "Boton_PUMV_Cancelar_Invierno": {},
    "Boton_PUMV_Cancelar_Verano": {},
    "Boton_PUMV_Comprobar_Verano": {},
    "Boton_PUMV_Invierno": {},
    "Boton_PUMV_Verano": {},
    "BotonAñadirBaja": {},
    "BotonAñadirDAP": {},
    "BotonAñadirDLE": {},
    "BotonAñadirVacaciones": {},
    "BotonCalcularCalendario": {},
    "BotonConfigurarCalendario": {},
    "botonEnviar": {},
    "BotonModificarDLE": {},
    "BotonModificarVacaciones": {},
    "botonNuevo": {},
    "BotonPortalEmpleados": {},
    "botonReinicio": {},
    "btn_aceptar_baja": {},
    "btn_aceptar_PUAAP": {},
    "btn_aceptar_PUALE": {},
    "btn_aceptar_PUMLE": {},
    "btn_cancelar_baja": {},
    "btn_cancelar_PUAAP": {},
    "btn_cancelar_PUALE": {},
    "btn_cancelar_PUMLE": {},
    "Button1": {},
    "Button2": {},
    "Button2_2": {},
    "Button7_5": {},
    "ButtonAceptar": {},
    "Buttoncancelar": {},
    "Buttonconfirmar": {},
    "ButtonEnviar": {},
    "Calendario": {},
    "ConfiguracionCalendario": {},
    "Consulta": {},
    "ConsultaEmpleadosTitle": {},
    "ConsultarVacaciones": {},
    "Contraseña_DataCard1": {},
    "Contraseña_DataCard2": {},
    "Cuadro_Espera": {},
    "Cuadro_PUAV": {},
    "Cuadro_PUAV_Invierno": {},
    "Cuadro_PUAV_Invierno_1": {},
    "Cuadro_PUAV_Verano": {},
    "Cuadro_PUAV_Verano_1": {},
    "Cuadro_PUMV": {},
    "DataCardKey1": {},
    "DataCardKey10": {},
    "DataCardKey11": {},
    "DataCardKey12": {},
    "DataCardKey13": {},
    "DataCardKey14": {},
    "DataCardKey15": {},
    "DataCardKey16": {},
    "DataCardKey17": {},
    "DataCardKey18": {},
    "DataCardKey19": {},
    "DataCardKey2": {},
    "DataCardKey20": {},
    "DataCardKey21": {},
    "DataCardKey22": {},
    "DataCardKey23": {},
    "DataCardKey24": {},
    "DataCardKey25": {},
    "DataCardKey26": {},
    "DataCardKey3": {},
    "DataCardKey4": {},
    "DataCardKey5": {},
    "DataCardKey6": {},
    "DataCardKey7": {},
    "DataCardKey8": {},
    "DataCardKey9": {},
    "DataCardValue1": {},
    "DataCardValue10": {},
    "DataCardValue11": {},
    "DataCardValue12": {},
    "DataCardValue13": {},
    "DataCardValue14": {},
    "DataCardValue15": {},
    "DataCardValue16": {},
    "DataCardValue17": {},
    "DataCardValue18": {},
    "DataCardValue19": {},
    "DataCardValue2": {},
    "DataCardValue20": {},
    "DataCardValue21": {},
    "DataCardValue22": {},
    "DataCardValue23": {},
    "DataCardValue24": {},
    "DataCardValue3": {},
    "DataCardValue4": {},
    "DataCardValue5": {},
    "DataCardValue6": {},
    "DataCardValue7": {},
    "DataCardValue8": {},
    "DataCardValue9": {},
    "Datos adjuntos_DataCard1": {},
    "Datos adjuntos_DataCard2": {},
    "Datos adjuntos_DataCard3": {},
    "Departamento_DataCard1": {},
    "Departamento_DataCard2": {},
    "Departamento_DataCard3": {},
    "Departamentos": {},
    "DiasSemana": {},
    "DNI_DataCard1": {},
    "DNI_DataCard2": {},
    "DNI_DataCard3": {},
    "dp_ALE1": {},
    "dp_ALE2": {},
    "dp_Fecha_PUAAP": {},
    "dp_Fin_Verano": {},
    "dp_FinInvierno": {},
    "dp_FinInvierno2": {},
    "dp_FinPeticion": {},
    "dp_inicio_baja": {},
    "dp_InicioInvierno": {},
    "dp_InicioInvierno2": {},
    "dp_InicioPeticion": {},
    "dp_InicioVerano": {},
    "dp_MLE1": {},
    "dp_MLE2": {},
    "dp_PUAV_Dia_Inicio_Verano_1": {},
    "dp_PUAV_Dia_Inicio_Verano_2": {},
    "dp_PUAV_Dia_Inicio_Verano_3": {},
    "dp_PUMV_Dia_Inicio_Verano_1": {},
    "dp_PUMV_Dia_Inicio_Verano_2": {},
    "dp_PUMV_Dia_Inicio_Verano_3": {},
    "Dropdown1": {},
    "Dropdown2": {},
    "Dropdown4": {},
    "ErrorMessage1": {},
    "ErrorMessage10": {},
    "ErrorMessage11": {},
    "ErrorMessage12": {},
    "ErrorMessage13": {},
    "ErrorMessage14": {},
    "ErrorMessage15": {},
    "ErrorMessage16": {},
    "ErrorMessage17": {},
    "ErrorMessage18": {},
    "ErrorMessage19": {},
    "ErrorMessage2": {},
    "ErrorMessage20": {},
    "ErrorMessage3": {},
    "ErrorMessage4": {},
    "ErrorMessage5": {},
    "ErrorMessage6": {},
    "ErrorMessage7": {},
    "ErrorMessage8": {},
    "ErrorMessage9": {},
    "EsAdmin_DataCard1": {},
    "EsAdmin_DataCard2": {},
    "EsAdmin_DataCard3": {},
    "Fecha Nacimiento_DataCard1": {},
    "Fecha Nacimiento_DataCard2": {},
    "Fecha Nacimiento_DataCard3": {},
    "FiltroDepartamento": {},
    "Firma_DataCard1": {},
    "Firma_DataCard2": {},
    "Firma_DataCard3": {},
    "FlechaSiguiente": {},
    "FondoPopUp": {},
    "FormNuevoEmpleado": {},
    "FormularioEmpleados": {},
    "FormularioModificar": {},
    "GaleriaNombres": {},
    "GaleriaNombrestemplate1": {},
    "Gallery1": {},
    "Gallery2": {},
    "GalleryCalendario": {},
    "galleryTemplate1": {},
    "galleryTemplate2": {},
    "galleryTemplate3": {},
    "Host": {},
    "Icon1": {},
    "Icon1_1": {},
    "Icon2": {},
    "Icon221": {},
    "Icon223": {},
    "Icon3": {},
    "Icon4": {},
    "IconInfo": {},
    "Icono_No_Ver_Contraseña": {},
    "Icono_Ver_Contraseña": {},
    "IconoAlerta": {},
    "IconoBorrar": {},
    "IconoBusqueda": {},
    "IconoDerecha": {},
    "IconoIzquierda": {},
    "IconoModificar": {},
    "IconoRetroceso": {},
    "IconoVolver": {},
    "IconRetrocede": {},
    "Image1": {},
    "Image4": {},
    "ImagenInvescon": {},
    "Label_espera": {},
    "Label1": {},
    "Label10": {},
    "Label11": {},
    "Label12": {},
    "Label12_1": {},
    "Label12_2": {},
    "Label12_3": {},
    "Label12_4": {},
    "Label12_5": {},
    "Label12_6": {},
    "Label12_7": {},
    "Label12_8": {},
    "Label13": {},
    "Label13_1": {},
    "Label13_2": {},
    "Label14": {},
    "Label15": {},
    "Label16": {},
    "Label17": {},
    "Label18": {},
    "Label2": {},
    "Label2_1": {},
    "Label20": {},
    "Label21": {},
    "Label22": {},
    "Label22_1": {},
    "Label221": {},
    "Label221_1": {},
    "Label3": {},
    "Label4": {},
    "Label5": {},
    "Label6": {},
    "Label7": {},
    "Label7_1": {},
    "Label8": {},
    "Label8_1": {},
    "Label9": {},
    "Label9_2": {},
    "Label9_3": {},
    "Label9_4": {},
    "Label9_5": {},
    "Label9_6": {},
    "Label9_7": {},
    "LabelAño": {},
    "LabelDiaCal": {},
    "LabelDomingo": {},
    "LabelEventoCal": {},
    "LabelJueves": {},
    "LabelLunes": {},
    "LabelMartes": {},
    "LabelMes": {},
    "LabelMiercoles": {},
    "LabelSabado": {},
    "LabelViernes": {},
    "Login": {},
    "Modificar": {},
    "Nombre_DataCard1": {},
    "Nombre_DataCard2": {},
    "Nombre_DataCard4": {},
    "NombreApellido": {},
    "Nuevo": {},
    "PenInput1": {},
    "PenInput2": {},
    "PopUp_AñadirAP": {},
    "PopUp_AñadirLE": {},
    "PopUp_Baja": {},
    "PopUp_ModificarLE": {},
    "PopUpAñadirVacaciones": {},
    "PopupCambio": {},
    "PopUpEliminar": {},
    "PopUpModificarVacaciones": {},
    "PUAV_Invierno": {},
    "PUAV_Verano": {},
    "PUMV_Invierno": {},
    "PUMV_Verano": {},
    "rb_PUAV_Invierno": {},
    "rb_PUAV_Verano": {},
    "rb_PUMV_Invierno": {},
    "rb_PUMV_Verano": {},
    "Rectangle1": {},
    "Rectangle10": {},
    "Rectangle1Sup": {},
    "Rectangle2": {},
    "Rectangle221": {},
    "Rectangle221_1": {},
    "Rectangle223": {},
    "Rectangle223_1": {},
    "Rectangle224": {},
    "Rectangle3": {},
    "Rectangle4": {},
    "Rectangle5": {},
    "Rectangle6": {},
    "Rectangle7": {},
    "Rectangle7_1": {},
    "Rectangle7_2": {},
    "Rectangle8": {},
    "RectangleGen": {},
    "RectangleModificar": {},
    "RectanglePopModificado": {},
    "RectanglePopUpEliminar": {},
    "RectangleSup": {},
    "RectangleSuperior": {},
    "RectanguloEmpleado": {},
    "ScInicial": {},
    "Separator2": {},
    "SeparatorEmpleado": {},
    "StarVisible1": {},
    "StarVisible10": {},
    "StarVisible11": {},
    "StarVisible12": {},
    "StarVisible13": {},
    "StarVisible14": {},
    "StarVisible15": {},
    "StarVisible16": {},
    "StarVisible17": {},
    "StarVisible18": {},
    "StarVisible19": {},
    "StarVisible2": {},
    "StarVisible20": {},
    "StarVisible3": {},
    "StarVisible4": {},
    "StarVisible5": {},
    "StarVisible6": {},
    "StarVisible7": {},
    "StarVisible8": {},
    "StarVisible9": {},
    "Subtitle2": {},
    "SubtitleDepartamento": {},
    "TextInput1": {},
    "TextInput2": {},
    "TextModificado": {},
    "TextoBusqueda": {},
    "TextoPopUpEliminar": {},
    "Title2": {},
    "TituloModificar": {},
    "tituloNuevoEmpleado": {},
    "TopBar": {},
    "txt_Contraseña_Login": {},
    "txt_duracion_baja": {},
    "txt_Usuario_Login": {},
    "VentanaEspera": {}
  },
  "PCFDynamicSchemaForIRRetrievalEntry": {},
  "PCFTemplateEntry": {},
  "PublishOrderIndices": {
    "Apellidos_DataCard1": 170,
    "Apellidos_DataCard2": 212,
    "Apellidos_DataCard3": 265,
    "App": 0,
    "Body1": 321,
    "Boton_Entrar_Login": 9,
    "Boton_PUAV_Aceptar_Invierno": 97,
    "Boton_PUAV_Aceptar_Verano": 113,
    "Boton_PUAV_Cancelar": 44,
    "Boton_PUAV_Cancelar_Invierno": 95,
    "Boton_PUAV_Cancelar_Verano": 112,
    "Boton_PUAV_Comprobar_Verano": 114,
    "Boton_PUAV_Invierno": 93,
    "Boton_PUAV_Verano": 91,
    "Boton_PUMV_Aceptar_Invierno": 103,
    "Boton_PUMV_Aceptar_Verano": 116,
    "Boton_PUMV_Cancelar": 51,
    "Boton_PUMV_Cancelar_Invierno": 102,
    "Boton_PUMV_Cancelar_Verano": 115,
    "Boton_PUMV_Comprobar_Verano": 117,
    "Boton_PUMV_Invierno": 99,
    "Boton_PUMV_Verano": 98,
    "BotonAñadirBaja": 15,
    "BotonAñadirDAP": 18,
    "BotonAñadirDLE": 16,
    "BotonAñadirVacaciones": 11,
    "BotonCalcularCalendario": 10,
    "BotonConfigurarCalendario": 20,
    "botonEnviar": 254,
    "BotonModificarDLE": 17,
    "BotonModificarVacaciones": 14,
    "botonNuevo": 252,
    "BotonPortalEmpleados": 21,
    "botonReinicio": 253,
    "btn_aceptar_baja": 111,
    "btn_aceptar_PUAAP": 105,
    "btn_aceptar_PUALE": 109,
    "btn_aceptar_PUMLE": 107,
    "btn_cancelar_baja": 110,
    "btn_cancelar_PUAAP": 104,
    "btn_cancelar_PUALE": 108,
    "btn_cancelar_PUMLE": 106,
    "Button1": 300,
    "Button2": 327,
    "Button2_2": 141,
    "Button7_5": 19,
    "ButtonAceptar": 311,
    "Buttoncancelar": 199,
    "Buttonconfirmar": 200,
    "ButtonEnviar": 312,
    "Calendario": 3,
    "ConfiguracionCalendario": 112,
    "Consulta": 137,
    "ConsultaEmpleadosTitle": 155,
    "ConsultarVacaciones": 0,
    "Contraseña_DataCard1": 222,
    "Contraseña_DataCard2": 275,
    "Cuadro_Espera": 23,
    "Cuadro_PUAV": 39,
    "Cuadro_PUAV_Invierno": 42,
    "Cuadro_PUAV_Invierno_1": 67,
    "Cuadro_PUAV_Verano": 26,
    "Cuadro_PUAV_Verano_1": 28,
    "Cuadro_PUMV": 49,
    "DataCardKey1": 209,
    "DataCardKey10": 229,
    "DataCardKey11": 244,
    "DataCardKey12": 249,
    "DataCardKey13": 224,
    "DataCardKey14": 267,
    "DataCardKey15": 262,
    "DataCardKey16": 272,
    "DataCardKey17": 282,
    "DataCardKey18": 297,
    "DataCardKey19": 304,
    "DataCardKey2": 168,
    "DataCardKey20": 239,
    "DataCardKey21": 234,
    "DataCardKey22": 277,
    "DataCardKey23": 287,
    "DataCardKey24": 292,
    "DataCardKey25": 182,
    "DataCardKey26": 185,
    "DataCardKey3": 171,
    "DataCardKey4": 175,
    "DataCardKey5": 179,
    "DataCardKey6": 188,
    "DataCardKey7": 192,
    "DataCardKey8": 214,
    "DataCardKey9": 219,
    "DataCardValue1": 169,
    "DataCardValue10": 230,
    "DataCardValue11": 250,
    "DataCardValue12": 225,
    "DataCardValue13": 268,
    "DataCardValue14": 263,
    "DataCardValue15": 273,
    "DataCardValue16": 283,
    "DataCardValue17": 305,
    "DataCardValue18": 240,
    "DataCardValue19": 235,
    "DataCardValue2": 172,
    "DataCardValue20": 278,
    "DataCardValue21": 288,
    "DataCardValue22": 293,
    "DataCardValue23": 183,
    "DataCardValue24": 186,
    "DataCardValue3": 176,
    "DataCardValue4": 180,
    "DataCardValue5": 189,
    "DataCardValue6": 193,
    "DataCardValue7": 210,
    "DataCardValue8": 215,
    "DataCardValue9": 220,
    "Datos adjuntos_DataCard1": 190,
    "Datos adjuntos_DataCard2": 247,
    "Datos adjuntos_DataCard3": 302,
    "Departamento_DataCard1": 173,
    "Departamento_DataCard2": 227,
    "Departamento_DataCard3": 280,
    "Departamentos": 190,
    "DiasSemana": 58,
    "DNI_DataCard1": 232,
    "DNI_DataCard2": 285,
    "DNI_DataCard3": 181,
    "dp_ALE1": 88,
    "dp_ALE2": 80,
    "dp_Fecha_PUAAP": 86,
    "dp_Fin_Verano": 139,
    "dp_FinInvierno": 133,
    "dp_FinInvierno2": 140,
    "dp_FinPeticion": 138,
    "dp_inicio_baja": 85,
    "dp_InicioInvierno": 130,
    "dp_InicioInvierno2": 137,
    "dp_InicioPeticion": 131,
    "dp_InicioVerano": 132,
    "dp_MLE1": 83,
    "dp_MLE2": 92,
    "dp_PUAV_Dia_Inicio_Verano_1": 78,
    "dp_PUAV_Dia_Inicio_Verano_2": 90,
    "dp_PUAV_Dia_Inicio_Verano_3": 96,
    "dp_PUMV_Dia_Inicio_Verano_1": 82,
    "dp_PUMV_Dia_Inicio_Verano_2": 94,
    "dp_PUMV_Dia_Inicio_Verano_3": 101,
    "Dropdown1": 322,
    "Dropdown2": 342,
    "Dropdown4": 340,
    "ErrorMessage1": 211,
    "ErrorMessage10": 264,
    "ErrorMessage11": 274,
    "ErrorMessage12": 284,
    "ErrorMessage13": 301,
    "ErrorMessage14": 306,
    "ErrorMessage15": 226,
    "ErrorMessage16": 241,
    "ErrorMessage17": 236,
    "ErrorMessage18": 279,
    "ErrorMessage19": 289,
    "ErrorMessage2": 177,
    "ErrorMessage20": 294,
    "ErrorMessage3": 194,
    "ErrorMessage4": 216,
    "ErrorMessage5": 221,
    "ErrorMessage6": 231,
    "ErrorMessage7": 246,
    "ErrorMessage8": 251,
    "ErrorMessage9": 269,
    "EsAdmin_DataCard1": 237,
    "EsAdmin_DataCard2": 290,
    "EsAdmin_DataCard3": 184,
    "Fecha Nacimiento_DataCard1": 178,
    "Fecha Nacimiento_DataCard2": 217,
    "Fecha Nacimiento_DataCard3": 270,
    "FiltroDepartamento": 156,
    "Firma_DataCard1": 242,
    "Firma_DataCard2": 187,
    "Firma_DataCard3": 295,
    "FlechaSiguiente": 162,
    "FondoPopUp": 12,
    "FormNuevoEmpleado": 206,
    "FormularioEmpleados": 166,
    "FormularioModificar": 259,
    "GaleriaNombres": 158,
    "GaleriaNombrestemplate1": 159,
    "Gallery1": 317,
    "Gallery2": 331,
    "GalleryCalendario": 73,
    "galleryTemplate1": 318,
    "galleryTemplate2": 332,
    "galleryTemplate3": 74,
    "Host": 0,
    "Icon1": 143,
    "Icon1_1": 315,
    "Icon2": 120,
    "Icon221": 148,
    "Icon223": 149,
    "Icon3": 150,
    "Icon4": 330,
    "IconInfo": 309,
    "Icono_No_Ver_Contraseña": 7,
    "Icono_Ver_Contraseña": 8,
    "IconoAlerta": 197,
    "IconoBorrar": 202,
    "IconoBusqueda": 153,
    "IconoDerecha": 66,
    "IconoIzquierda": 56,
    "IconoModificar": 201,
    "IconoRetroceso": 204,
    "IconoVolver": 154,
    "IconRetrocede": 258,
    "Image1": 1,
    "Image4": 299,
    "ImagenInvescon": 161,
    "Label_espera": 60,
    "Label1": 53,
    "Label10": 48,
    "Label11": 119,
    "Label12": 128,
    "Label12_1": 129,
    "Label12_2": 127,
    "Label12_3": 135,
    "Label12_4": 136,
    "Label12_5": 134,
    "Label12_6": 125,
    "Label12_7": 126,
    "Label12_8": 124,
    "Label13": 316,
    "Label13_1": 325,
    "Label13_2": 323,
    "Label14": 326,
    "Label15": 329,
    "Label16": 336,
    "Label17": 334,
    "Label18": 335,
    "Label2": 54,
    "Label2_1": 69,
    "Label20": 337,
    "Label21": 341,
    "Label22": 343,
    "Label22_1": 339,
    "Label221": 144,
    "Label221_1": 314,
    "Label3": 45,
    "Label4": 3,
    "Label5": 5,
    "Label6": 2,
    "Label7": 52,
    "Label7_1": 70,
    "Label8": 77,
    "Label8_1": 81,
    "Label9": 55,
    "Label9_2": 36,
    "Label9_3": 71,
    "Label9_4": 87,
    "Label9_5": 35,
    "Label9_6": 72,
    "Label9_7": 89,
    "LabelAño": 41,
    "LabelDiaCal": 76,
    "LabelDomingo": 65,
    "LabelEventoCal": 75,
    "LabelJueves": 62,
    "LabelLunes": 57,
    "LabelMartes": 59,
    "LabelMes": 32,
    "LabelMiercoles": 61,
    "LabelSabado": 64,
    "LabelViernes": 63,
    "Login": 206,
    "Modificar": 217,
    "Nombre_DataCard1": 167,
    "Nombre_DataCard2": 207,
    "Nombre_DataCard4": 260,
    "NombreApellido": 163,
    "Nuevo": 276,
    "PenInput1": 245,
    "PenInput2": 298,
    "PopUp_AñadirAP": 47,
    "PopUp_AñadirLE": 25,
    "PopUp_Baja": 38,
    "PopUp_ModificarLE": 31,
    "PopUpAñadirVacaciones": 40,
    "PopupCambio": 308,
    "PopUpEliminar": 196,
    "PopUpModificarVacaciones": 50,
    "PUAV_Invierno": 43,
    "PUAV_Verano": 27,
    "PUMV_Invierno": 68,
    "PUMV_Verano": 29,
    "rb_PUAV_Invierno": 79,
    "rb_PUAV_Verano": 34,
    "rb_PUMV_Invierno": 84,
    "rb_PUMV_Verano": 33,
    "Rectangle1": 37,
    "Rectangle10": 333,
    "Rectangle1Sup": 255,
    "Rectangle2": 24,
    "Rectangle221": 142,
    "Rectangle221_1": 313,
    "Rectangle223": 145,
    "Rectangle223_1": 147,
    "Rectangle224": 146,
    "Rectangle3": 46,
    "Rectangle4": 0,
    "Rectangle5": 30,
    "Rectangle6": 118,
    "Rectangle7": 121,
    "Rectangle7_1": 123,
    "Rectangle7_2": 122,
    "Rectangle8": 328,
    "RectangleGen": 152,
    "RectangleModificar": 256,
    "RectanglePopModificado": 307,
    "RectanglePopUpEliminar": 195,
    "RectangleSup": 203,
    "RectangleSuperior": 151,
    "RectanguloEmpleado": 160,
    "ScInicial": 329,
    "Separator2": 338,
    "SeparatorEmpleado": 165,
    "StarVisible1": 208,
    "StarVisible10": 261,
    "StarVisible11": 271,
    "StarVisible12": 281,
    "StarVisible13": 296,
    "StarVisible14": 303,
    "StarVisible15": 223,
    "StarVisible16": 238,
    "StarVisible17": 233,
    "StarVisible18": 276,
    "StarVisible19": 286,
    "StarVisible2": 174,
    "StarVisible20": 291,
    "StarVisible3": 191,
    "StarVisible4": 213,
    "StarVisible5": 218,
    "StarVisible6": 228,
    "StarVisible7": 243,
    "StarVisible8": 248,
    "StarVisible9": 266,
    "Subtitle2": 320,
    "SubtitleDepartamento": 164,
    "TextInput1": 324,
    "TextInput2": 344,
    "TextModificado": 310,
    "TextoBusqueda": 157,
    "TextoPopUpEliminar": 198,
    "Title2": 319,
    "TituloModificar": 257,
    "tituloNuevoEmpleado": 205,
    "TopBar": 13,
    "txt_Contraseña_Login": 6,
    "txt_duracion_baja": 100,
    "txt_Usuario_Login": 4,
    "VentanaEspera": 22
  },
  "ResourcesJsonIndices": {
    "Image-logo": 1,
    "Image-SampleImage": 0,
    "Image-vacaciones": 2
  },
  "RuleScreenIdWithoutScreen": {},
  "TemplateVersions": {},
  "VolatileProperties": {
    "AnalysisLoadTime": 1.8559921,
    "ControlCount": {
      "attachments": 3,
      "button": 45,
      "combobox": 3,
      "datepicker": 22,
      "dropdown": 3,
      "form": 2,
      "formViewer": 1,
      "gallery": 3,
      "galleryTemplate": 3,
      "group": 15,
      "icon": 19,
      "image": 4,
      "inkControl": 2,
      "label": 128,
      "radio": 4,
      "rectangle": 31,
      "screen": 8,
      "text": 15,
      "toggleSwitch": 3,
      "typedDataCard": 26
    },
    "DeserializationLoadTime": 2.7973742
  },
  "WasLocalDatabaseReferencesEmpty": true
}